{
  "schema": "post-merge-smoke-v1",
  "run_at": "2026-06-24T00:51:28Z",
  "head_sha": "4841964e45f02d2c705ec5b534173672e10de82d",
  "all_passed": true,
  "tunnel_down": false,
  "unreachable_count": 0,
  "checks": [
    {
      "url": "https://demos.guitaralchemist.com/test",
      "status": 200,
      "ok": true,
      "latency_ms": 327,
      "size_bytes": 1391,
      "content_marker": "Guitar Alchemist",
      "content_marker_found": true,
      "unreachable": false,
      "gateway_error": false
    },
    {
      "url": "https://demos.guitaralchemist.com/chatbot/",
      "status": 200,
      "ok": true,
      "latency_ms": 157,
      "size_bytes": 39727,
      "content_marker": "GA Chatbot",
      "content_marker_found": true,
      "unreachable": false,
      "gateway_error": false
    },
    {
      "url": "https://demos.guitaralchemist.com/dev-data/manifest",
      "status": 200,
      "ok": true,
      "latency_ms": 6288,
      "size_bytes": 192448,
      "content_marker": "schema_version",
      "content_marker_found": true,
      "unreachable": false,
      "gateway_error": false
    }
  ]
}
